Metadata-Version: 1.1
Name: imdb-series-scraper
Version: 1.0.7
Summary: scrape IMDB series and create metrics for statistics
Home-page: https://github.com/AdriaPadilla/imdb_series_scraper/
Author: Adrian Padilla
Author-email: adrian.padilla.m@gmail.com
License: UNKNOWN
Platform: UNKNOWN
Classifier: Programming Language :: Python :: 3
Classifier: License :: OSI Approved :: MIT License
Classifier: Operating System :: OS Independent
